<annotation>
	<folder>data gan</folder>
	<filename>material_miss_20_real_3.jpg</filename>
	<path>G:\bishe\data gan\material_miss_20_real.png</path>
	<source>
		<database>Unknown</database>
	</source>
	<size>
		<width>256</width>
		<height>256</height>
		<depth>3</depth>
	</size>
	<segmented>0</segmented>
	<object>
		<name>materiai_miss</name>
		<pose>Unspecified</pose>
		<truncated>0</truncated>
		<difficult>0</difficult>
		<bndbox>
			<xmin>68</xmin>
			<ymin>151</ymin>
			<xmax>126</xmax>
			<ymax>195</ymax>
		</bndbox>
	</object>
</annotation>